openwillis/speech/__init__.py
openwillis/speech/speech_attribute.py
openwillis/speech/config/speech.json
openwillis/speech/config/text.json
openwillis/speech/util/__init__.py
openwillis/speech/util/characteristics_util.py
openwillis/speech/util/speech/__init__.py
openwillis/speech/util/speech/coherence.py
openwillis/speech/util/speech/lexical.py
openwillis/speech/util/speech/pause.py
openwillis_speech-1.1.0.dist-info/METADATA
openwillis_speech-1.1.0.dist-info/WHEEL
openwillis_speech-1.1.0.dist-info/top_level.txt
openwillis_speech-1.1.0.dist-info/RECORD
