Metadata-Version: 2.4
Name: openwillis-speech
Version: 1.1.0
Summary: digital health measurement
Home-page: https://github.com/bklynhlth/openwillis
Author: bklynhlth
Author-email: admin@bklynhlth.com
License: Apache
Requires-Python: >=3.9, <3.13
Requires-Dist: vaderSentiment==3.3.2
Requires-Dist: nltk==3.9.1
Requires-Dist: lexicalrichness==0.5.1
Requires-Dist: pandas==2.2.3
Requires-Dist: pytest==8.3.4
Requires-Dist: transformers==4.46.3
Requires-Dist: sentence-transformers==3.3.1
Requires-Dist: huggingface-hub==0.26.3
Requires-Dist: spacy==3.7.5
Requires-Dist: tf-keras<=2.18.0,>=2.15.1
Dynamic: author
Dynamic: author-email
Dynamic: description-content-type
Dynamic: home-page
Dynamic: license
Dynamic: requires-dist
Dynamic: requires-python
Dynamic: summary
